aiotf/__init__.py
aiotf/__version__.py
aiotf/client.py
aiotf-0.1.0.dist-info/LICENSE.txt
aiotf-0.1.0.dist-info/METADATA
aiotf-0.1.0.dist-info/RECORD
aiotf-0.1.0.dist-info/WHEEL
aiotf-0.1.0.dist-info/top_level.txt
tensorflow_serving/__init__.py
