Metadata-Version: 2.1
Name: aiotf
Version: 0.1.0
Summary: Asyncio Tensorflow Serving Communication.
Home-page: https://github.com/brunoalano/aiotf
Author: Bruno Alano Medina
Author-email: bruno@neurologic.com.br
License: MIT
Platform: UNKNOWN
Classifier: Programming Language :: Python :: 3
Classifier: License :: OSI Approved :: MIT License
Classifier: Operating System :: OS Independent
Requires-Python: >=3.4
Requires-Dist: aiogrpc
Requires-Dist: tensorflow
